hanzo_tools/__init__.py
hanzo_tools/filesystem/__init__.py
hanzo_tools/filesystem/ast.py
hanzo_tools/filesystem/edit.py
hanzo_tools/filesystem/find.py
hanzo_tools/filesystem/read.py
hanzo_tools/filesystem/search.py
hanzo_tools/filesystem/tree.py
hanzo_tools/filesystem/write.py
hanzo_tools_filesystem-0.2.0.dist-info/METADATA
hanzo_tools_filesystem-0.2.0.dist-info/WHEEL
hanzo_tools_filesystem-0.2.0.dist-info/entry_points.txt
hanzo_tools_filesystem-0.2.0.dist-info/top_level.txt
hanzo_tools_filesystem-0.2.0.dist-info/RECORD
