Metadata-Version: 2.4
Name: hanzo-tools-filesystem
Version: 0.2.0
Summary: Filesystem tools for Hanzo AI - read, write, edit, search, find
Author-email: Hanzo Industries Inc <dev@hanzo.ai>
License: MIT
Project-URL: Homepage, https://github.com/hanzoai/python-sdk
Keywords: hanzo,tools,filesystem,mcp,ai
Classifier: Programming Language :: Python :: 3
Classifier: License :: OSI Approved :: MIT License
Classifier: Operating System :: OS Independent
Requires-Python: >=3.12
Requires-Dist: aiofiles>=24.1.0
Requires-Dist: grep-ast>=0.8.1
Requires-Dist: ffind>=1.3.0
Requires-Dist: watchdog>=6.0.0
Requires-Dist: mcp>=1.25.0
Requires-Dist: fastmcp>=2.14.1
Requires-Dist: pydantic>=2.12.5
Provides-Extra: dev
Requires-Dist: pytest>=7.0.0; extra == "dev"
Requires-Dist: ruff>=0.14.0; extra == "dev"
